download_toolbox/__init__.py
download_toolbox/base.py
download_toolbox/cli.py
download_toolbox/config.py
download_toolbox/dataset.py
download_toolbox/download.py
download_toolbox/interface.py
download_toolbox/location.py
download_toolbox/time.py
download_toolbox/utils.py
download_toolbox/data/__init__.py
download_toolbox/data/amsr.py
download_toolbox/data/aws.py
download_toolbox/data/cds.py
download_toolbox/data/esgf.py
download_toolbox/data/mars.py
download_toolbox/data/osisaf.py
download_toolbox/data/utils.py
download_toolbox/scratches/hres.py
download_toolbox/scratches/mars.py
download_toolbox-0.0.6.dist-info/AUTHORS.md
download_toolbox-0.0.6.dist-info/LICENSE
download_toolbox-0.0.6.dist-info/METADATA
download_toolbox-0.0.6.dist-info/WHEEL
download_toolbox-0.0.6.dist-info/entry_points.txt
download_toolbox-0.0.6.dist-info/top_level.txt
download_toolbox-0.0.6.dist-info/RECORD
