Metadata-Version: 2.1
Name: download-toolbox
Version: 0.0.6
Summary: Library for downloading and preprocessing data
Author: British Antarctic Survey / Alan Turing Institute
Maintainer-email: jambyr@bas.ac.uk
License: MIT License
Project-URL: Homepage, https://icenet.ai/
Project-URL: Source, https://github.com/antarctica/download-toolbox
Project-URL: Issue tracker, https://github.com/antarctica/download-toolbox/issues
Classifier: Development Status :: 3 - Alpha
Classifier: Environment :: Console
Classifier: Intended Audience :: Science/Research
Classifier: License :: OSI Approved :: MIT License
Classifier: Natural Language :: English
Classifier: Operating System :: POSIX
Classifier: Programming Language :: Python :: 3
Classifier: Programming Language :: Python :: 3.8
Classifier: Programming Language :: Python :: 3.9
Classifier: Programming Language :: Python :: 3.10
Classifier: Programming Language :: Python :: 3.11
Requires-Python: >=3.8
License-File: LICENSE
License-File: AUTHORS.md
Requires-Dist: boto3
Requires-Dist: cdsapi
Requires-Dist: cfgrib
Requires-Dist: dask[distributed]
Requires-Dist: eccodes
Requires-Dist: ecmwf-api-client
Requires-Dist: esgf-pyclient
Requires-Dist: motuclient
Requires-Dist: orjson
Requires-Dist: pandas
Requires-Dist: pip
Requires-Dist: pydap
Requires-Dist: setuptools
Requires-Dist: wheel
Requires-Dist: urllib3<2.0.0
Requires-Dist: xarray[io]
Provides-Extra: dev
Requires-Dist: watchdog; extra == "dev"
Requires-Dist: flake8; extra == "dev"
Requires-Dist: tox; extra == "dev"
Requires-Dist: coverage; extra == "dev"
Requires-Dist: twine; extra == "dev"
Requires-Dist: pytest; extra == "dev"
Requires-Dist: black; extra == "dev"
Requires-Dist: build; extra == "dev"
Requires-Dist: importlib-metadata; extra == "dev"
Requires-Dist: pre-commit; extra == "dev"
Requires-Dist: fsspec; extra == "dev"
Provides-Extra: docs
Requires-Dist: mkdocs; extra == "docs"
Requires-Dist: mkdocstrings[python]; extra == "docs"
Requires-Dist: markdown-include; extra == "docs"
Requires-Dist: mkdocs-material; extra == "docs"
